pytalises/__init__.py
pytalises/propagator.py
pytalises/wavefunction.py
pytalises-0.2.7.dist-info/LICENSE
pytalises-0.2.7.dist-info/METADATA
pytalises-0.2.7.dist-info/WHEEL
pytalises-0.2.7.dist-info/top_level.txt
pytalises-0.2.7.dist-info/RECORD
