Metadata-Version: 2.1
Name: pytalises
Version: 0.2.7
Summary: 
Home-page: http://github.com/savowe/pytalises
Author: Sascha Vowe
Author-email: sascha.vowe@posteo.de
License: GPL v3.0
Platform: UNKNOWN
Classifier: Programming Language :: Python :: 3
Classifier: Development Status :: 3 - Alpha
Classifier: License :: OSI Approved :: GNU General Public License v3 (GPLv3)
Classifier: Operating System :: OS Independent
Classifier: Topic :: Scientific/Engineering :: Physics
Requires-Python: >=3.6
Requires-Dist: numpy (>=1.19)
Requires-Dist: scipy (>=1.5)
Requires-Dist: numba (>=0.50)
Requires-Dist: pyfftw (>=0.12)
Requires-Dist: numexpr (>=2.7)
